LICENSE
MANIFEST.in
README.md
setup.py
pytoolsbrunojatoba/__init__.py
pytoolsbrunojatoba/github_api.py
pytoolsbrunojatoba.egg-info/PKG-INFO
pytoolsbrunojatoba.egg-info/SOURCES.txt
pytoolsbrunojatoba.egg-info/dependency_links.txt
pytoolsbrunojatoba.egg-info/not-zip-safe
pytoolsbrunojatoba.egg-info/requires.txt
pytoolsbrunojatoba.egg-info/top_level.txt